infra_enver/__init__.py
infra_enver/cache.py
infra_enver/config.py
infra_enver/infra_enver.py
infra_enver/infra_enver_exceptions.py
infra_flow-1.0.12.dist-info/METADATA
infra_flow-1.0.12.dist-info/WHEEL
infra_flow-1.0.12.dist-info/top_level.txt
infra_flow-1.0.12.dist-info/RECORD
