Metadata-Version: 2.1
Name: infra-flow
Version: 1.0.12
Summary: Infra Enver
Author: Daniil Vladimirov
License: MIT
Requires-Dist: requests
Requires-Dist: pydantic
Requires-Dist: redis
